sparrowSql/__init__.py
sparrowSql/mariaDB.py
sparrowSql/mysql.py
sparrowSql/oracle.py
sparrowSql/postgresql.py
sparrowSql/sparrow.py
sparrowSql/sqLite.py
sparrowSql/sqlserver.py
sparrowSql/tools/__init__.py
sparrowSql-0.1.8.4.dist-info/LICENSE.txt
sparrowSql-0.1.8.4.dist-info/METADATA
sparrowSql-0.1.8.4.dist-info/WHEEL
sparrowSql-0.1.8.4.dist-info/top_level.txt
sparrowSql-0.1.8.4.dist-info/RECORD
